Editing_gambar/Kecerahan.py
Editing_gambar/__init__.py
Editing_gambar/hitam_putih.py
Editing_gambar/pemotonganGambar.py
Editing_gambar/penambahanTeks.py
Editing_gambar/pencerminanGambar.py
Editing_gambar/rotasiGambar.py
Editing_gambar-0.3.0.dist-info/METADATA
Editing_gambar-0.3.0.dist-info/WHEEL
Editing_gambar-0.3.0.dist-info/top_level.txt
Editing_gambar-0.3.0.dist-info/RECORD
