Metadata-Version: 2.1
Name: Editing_gambar
Version: 0.3.0
Summary: Paket Python untuk pengolahan gambar
Home-page: https://github.com/Jeanjrg/Project-kelompok-3B-algoritma
Author: kelompok 3
Author-email: email@jeanbumbungan.com
License: MIT
Classifier: Programming Language :: Python :: 3
Classifier: License :: OSI Approved :: MIT License
Classifier: Operating System :: OS Independent
Requires-Python: >=3.7
Requires-Dist: Pillow>=8.0
